{
  "address": "nTqEj8gr65fCtYhoZNKbK4ri2QyMY7HvrFeBzVuFRqU",
  "metadata": {
    "name": "unite",
    "version": "0.1.0",
    "spec": "0.1.0",
    "description": "Created with Anchor"
  },
  "instructions": [
    {
      "name": "create_event",
      "discriminator": [
        49,
        219,
        29,
        203,
        22,
        98,
        100,
        87
      ],
      "accounts": [
        {
          "name": "organizer",
          "writable": true,
          "pda": {
            "seeds": [
              {
                "kind": "const",
                "value": [
                  111,
                  114,
                  103,
                  97,
                  110,
                  105,
                  122,
                  101,
                  114
                ]
              },
              {
                "kind": "account",
                "path": "authority"
              }
            ]
          }
        },
        {
          "name": "event",
          "writable": true,
          "pda": {
            "seeds": [
              {
                "kind": "const",
                "value": [
                  101,
                  118,
                  101,
                  110,
                  116
                ]
              },
              {
                "kind": "account",
                "path": "authority"
              },
              {
                "kind": "account",
                "path": "organizer.event_count",
                "account": "OrganizerAccount"
              }
            ]
          }
        },
        {
          "name": "authority",
          "writable": true,
          "signer": true
        },
        {
          "name": "system_program",
          "address": "11111111111111111111111111111111"
        }
      ],
      "args": [
        {
          "name": "title",
          "type": "string"
        },
        {
          "name": "description",
          "type": "string"
        },
        {
          "name": "deadline",
          "type": "i64"
        },
        {
          "name": "ticket_price",
          "type": "u64"
        },
        {
          "name": "quorum",
          "type": "u32"
        },
        {
          "name": "maximum_capacity",
          "type": "u32"
        }
      ]
    },
    {
      "name": "initialize_organizer",
      "discriminator": [
        223,
        252,
        246,
        108,
        132,
        141,
        11,
        217
      ],
      "accounts": [
        {
          "name": "organizer",
          "writable": true,
          "pda": {
            "seeds": [
              {
                "kind": "const",
                "value": [
                  111,
                  114,
                  103,
                  97,
                  110,
                  105,
                  122,
                  101,
                  114
                ]
              },
              {
                "kind": "account",
                "path": "authority"
              }
            ]
          }
        },
        {
          "name": "authority",
          "writable": true,
          "signer": true
        },
        {
          "name": "system_program",
          "address": "11111111111111111111111111111111"
        }
      ],
      "args": []
    }
  ],
  "accounts": [
    {
      "name": "EventAccount",
      "discriminator": [
        98,
        136,
        32,
        165,
        133,
        231,
        243,
        154
      ]
    },
    {
      "name": "OrganizerAccount",
      "discriminator": [
        68,
        201,
        38,
        125,
        135,
        112,
        11,
        149
      ]
    }
  ],
  "types": [
    {
      "name": "EventAccount",
      "type": {
        "kind": "struct",
        "fields": [
          {
            "name": "organizer",
            "type": "pubkey"
          },
          {
            "name": "title",
            "type": "string"
          },
          {
            "name": "description",
            "type": "string"
          },
          {
            "name": "deadline",
            "type": "i64"
          },
          {
            "name": "ticket_price",
            "type": "u64"
          },
          {
            "name": "quorum",
            "type": "u32"
          },
          {
            "name": "attendees",
            "type": "u32"
          },
          {
            "name": "maximum_capacity",
            "type": "u32"
          },
          {
            "name": "is_cancelled",
            "type": "bool"
          },
          {
            "name": "is_confirmed",
            "type": "bool"
          },
          {
            "name": "bump",
            "type": "u8"
          }
        ]
      }
    },
    {
      "name": "OrganizerAccount",
      "type": {
        "kind": "struct",
        "fields": [
          {
            "name": "authority",
            "type": "pubkey"
          },
          {
            "name": "event_count",
            "type": "u32"
          }
        ]
      }
    }
  ]
}